memento/__init__.py
memento/bootstrap.py
memento/estimator.py
memento/hypothesis_test.py
memento/main.py
memento/simulate.py
memento/util.py
memento/wrappers.py
memento_de-0.1.2.dist-info/LICENSE
memento_de-0.1.2.dist-info/METADATA
memento_de-0.1.2.dist-info/WHEEL
memento_de-0.1.2.dist-info/top_level.txt
memento_de-0.1.2.dist-info/RECORD
